clipboard/__init__.py
clipboard/_c_interface.py
clipboard/clipboard.py
clipboard/constants.py
clipboard/errors.py
clipboard/formats.py
clipboard/html_clipboard.py
clip_util-0.1.28.dist-info/LICENSE
clip_util-0.1.28.dist-info/METADATA
clip_util-0.1.28.dist-info/WHEEL
clip_util-0.1.28.dist-info/top_level.txt
clip_util-0.1.28.dist-info/RECORD
