Metadata-Version: 2.1
Name: clip-util
Version: 0.1.28
Summary: Clipboard utilities for use with Python.
Author-email: "Kyle L. Davis" <aceofspades5757.github@gmail.com>
Maintainer-email: "Kyle L. Davis" <aceofspades5757.github@gmail.com>
License: MIT License
Project-URL: Homepage, https://github.com/AceofSpades5757/clip-util
Project-URL: Documentation, https://clip-util.readthedocs.io/en/latest/
Project-URL: Author, https://github.com/AceofSpades5757
Project-URL: Repository, https://github.com/AceofSpades5757/clip-util
Project-URL: Issues, https://github.com/AceofSpades5757/clip-util/issues
Keywords: clipboard,html,rtf,unicode
Classifier: Programming Language :: Python :: 3
Classifier: Operating System :: Microsoft :: Windows
Classifier: License :: OSI Approved :: MIT License
Classifier: Development Status :: 4 - Beta
Classifier: Programming Language :: Python :: 3.9
Classifier: Programming Language :: Python :: 3.10
Classifier: Programming Language :: Python :: 3.11
Classifier: Programming Language :: Python :: 3.12
Classifier: Intended Audience :: Developers
Classifier: Topic :: Software Development :: Libraries
Classifier: Topic :: Software Development :: Libraries :: Python Modules
Classifier: Topic :: Utilities
Classifier: Typing :: Typed
Requires-Python: >=3.9
License-File: LICENSE
Provides-Extra: build
Requires-Dist: build ; extra == 'build'
Requires-Dist: setuptools ; extra == 'build'
Provides-Extra: dev
Requires-Dist: clip-util[build] ; extra == 'dev'
Requires-Dist: clip-util[test] ; extra == 'dev'
Requires-Dist: pre-commit ; extra == 'dev'
Requires-Dist: mypy ; extra == 'dev'
Provides-Extra: test
Requires-Dist: tox ; extra == 'test'
Requires-Dist: tox-gh-actions ; extra == 'test'
